sphinx_html5_basic_theme/setup_get_path.py
sphinx_html5_basic_theme/sphinx_html5_translator.py
sphinx_html5_basic_theme/__init__.py
sphinx_html5_basic_theme/doc/conf.py
sphinx_html5_basic_theme/doc/index.rst
sphinx_html5_basic_theme/doc/make.bat
sphinx_html5_basic_theme/doc/Makefile
sphinx_html5_basic_theme/doc/README.rst
sphinx_html5_basic_theme/doc/README_ja.rst
sphinx_html5_basic_theme/html5_basic/defindex.html
sphinx_html5_basic_theme/html5_basic/domainindex.html
sphinx_html5_basic_theme/html5_basic/genindex-single.html
sphinx_html5_basic_theme/html5_basic/genindex-split.html
sphinx_html5_basic_theme/html5_basic/genindex.html
sphinx_html5_basic_theme/html5_basic/globaltoc.html
sphinx_html5_basic_theme/html5_basic/layout.html
sphinx_html5_basic_theme/html5_basic/localtoc.html
sphinx_html5_basic_theme/html5_basic/opensearch.xml
sphinx_html5_basic_theme/html5_basic/page.html
sphinx_html5_basic_theme/html5_basic/relations.html
sphinx_html5_basic_theme/html5_basic/search.html
sphinx_html5_basic_theme/html5_basic/searchbox.html
sphinx_html5_basic_theme/html5_basic/searchresults.html
sphinx_html5_basic_theme/html5_basic/sourcelink.html
sphinx_html5_basic_theme/html5_basic/theme.conf
sphinx_html5_basic_theme/html5_basic/changes/frameset.html
sphinx_html5_basic_theme/html5_basic/changes/rstsource.html
sphinx_html5_basic_theme/html5_basic/changes/versionchanges.html
sphinx_html5_basic_theme/html5_basic/static/ajax-loader.gif
sphinx_html5_basic_theme/html5_basic/static/basic.css_t
sphinx_html5_basic_theme/html5_basic/static/comment-bright.png
sphinx_html5_basic_theme/html5_basic/static/comment-close.png
sphinx_html5_basic_theme/html5_basic/static/comment.png
sphinx_html5_basic_theme/html5_basic/static/doctools.js
sphinx_html5_basic_theme/html5_basic/static/down-pressed.png
sphinx_html5_basic_theme/html5_basic/static/down.png
sphinx_html5_basic_theme/html5_basic/static/file.png
sphinx_html5_basic_theme-1.0.5.dist-info/DESCRIPTION.rst
sphinx_html5_basic_theme-1.0.5.dist-info/entry_points.txt
sphinx_html5_basic_theme-1.0.5.dist-info/METADATA
sphinx_html5_basic_theme-1.0.5.dist-info/metadata.json
sphinx_html5_basic_theme-1.0.5.dist-info/RECORD
sphinx_html5_basic_theme-1.0.5.dist-info/top_level.txt
sphinx_html5_basic_theme-1.0.5.dist-info/WHEEL
