Metadata-Version: 2.0
Name: sphinx-html5-basic-theme
Version: 1.0.5
Summary: Enable Sphinx to generate HTML5 valid files
Home-page: http://h12u.com/sphinx/html5_basic_theme/
Author: Suzumizaki-Kimitaka(鈴見咲 君高)
Author-email: info@h12u.com
License: BSD
Platform: any
Classifier: Framework :: Sphinx :: Extension
Classifier: Framework :: Sphinx :: Theme
Classifier: Intended Audience :: Developers
Classifier: License :: OSI Approved :: BSD License
Classifier: Operating System :: OS Independent
Classifier: Topic :: Documentation :: Sphinx
Classifier: Topic :: Software Development :: Documentation
Requires-Dist: sphinx (>=1.3)
